DataBaseManager/__init__.py
DataBaseManager/__main__.py
DataBaseManager-1.0.0.dist-info/LICENSE
DataBaseManager-1.0.0.dist-info/METADATA
DataBaseManager-1.0.0.dist-info/WHEEL
DataBaseManager-1.0.0.dist-info/dependency_links.txt
DataBaseManager-1.0.0.dist-info/top_level.txt
DataBaseManager-1.0.0.dist-info/RECORD
