Metadata-Version: 2.1
Name: DataBaseManager
Version: 1.0.0
Summary: A simple Database manager. You can manage database simply without using SQL or any other query language. The Inputs and outputs are in the form of JSON so you can simply share the data across networks. A simple SQL shell was attached to do more with Your Db.
Home-page: https://abam.herokuapp/projects/DataBaseManager
Author: Aswanth Vc
Author-email: no-mail@example.com
License: UNKNOWN
Keywords: Database manager,database,manager,python database manager,sqlite manger,sqlite,mysql,mysqlmanager,db manager,multi processer,fast database manager,DataBaseManager,Data Base,db,muliti process database manager,multi,mulitprocess,manage multiple database at the same time
Platform: UNKNOWN
Classifier: Programming Language :: Python :: 3
Classifier: License :: OSI Approved :: MIT License
Classifier: Operating System :: OS Independent
Requires-Python: >=3.6
License-File: LICENSE
Requires-Dist: Languages
